igfold/IgFoldRunner.py
igfold/__init__.py
igfold/model/IgFold.py
igfold/model/__init__.py
igfold/model/interface.py
igfold/model/components/GraphTransformer.py
igfold/model/components/IPABlock.py
igfold/model/components/IPATransformer.py
igfold/model/components/TriangleGraphTransformer.py
igfold/model/components/TriangleMultiplicativeModule.py
igfold/model/components/__init__.py
igfold/refine/__init__.py
igfold/refine/openmm_ref.py
igfold/refine/pyrosetta_ref.py
igfold/trained_models/IgFold/.DS_Store
igfold/trained_models/IgFold/LICENSE.md
igfold/trained_models/IgFold/igfold_1.ckpt
igfold/trained_models/IgFold/igfold_2.ckpt
igfold/trained_models/IgFold/igfold_3.ckpt
igfold/trained_models/IgFold/igfold_5.ckpt
igfold/training/__init__.py
igfold/training/utils.py
igfold/utils/__init__.py
igfold/utils/ab_metrics.py
igfold/utils/abnumber_.py
igfold/utils/constants.py
igfold/utils/coordinates.py
igfold/utils/embed.py
igfold/utils/fasta.py
igfold/utils/folding.py
igfold/utils/general.py
igfold/utils/geometry.py
igfold/utils/pdb.py
igfold/utils/tensor.py
igfold/utils/transforms.py
igfold/utils/visualize.py
igfold-0.4.0.dist-info/LICENSE.md
igfold-0.4.0.dist-info/METADATA
igfold-0.4.0.dist-info/WHEEL
igfold-0.4.0.dist-info/top_level.txt
igfold-0.4.0.dist-info/RECORD
