Metadata-Version: 2.1
Name: igfold
Version: 0.4.0
License-File: LICENSE.md
Requires-Dist: antiberty >=0.1.1
Requires-Dist: biopython >=1.79
Requires-Dist: einops >=0.3.0
Requires-Dist: pytorch-lightning <1.9.0,>=1.5.10
Requires-Dist: torch >=1.7.1
